chbencode.py
chbencode-1.0.0.dist-info/METADATA
chbencode-1.0.0.dist-info/WHEEL
chbencode-1.0.0.dist-info/top_level.txt
chbencode-1.0.0.dist-info/RECORD
