Metadata-Version: 2.2
Name: chbencode
Version: 1.0.0
Summary: Encode string data by zlib, base64 invert etc.
Author-email: Marko <py.markop@icloud.com>
License: MIT
Project-URL: Homepage, https://github.com/py.marko/repository
Classifier: Programming Language :: Python :: 3
Classifier: License :: OSI Approved :: MIT License
Classifier: Operating System :: OS Independent
Requires-Python: >=3.7
